zundler/__init__.py
zundler/__main__.py
zundler/args.py
zundler/embed.py
zundler/assets/LICENSE
zundler/assets/init.css
zundler/assets/init.html
zundler/assets/inject_post.js
zundler/assets/inject_pre.js
zundler/assets/zundler_bootstrap.js
zundler/assets/zundler_common.js
zundler/assets/zundler_main.js
zundler/sphinxext/__init__.py
zundler-0.3.0.dist-info/METADATA
zundler-0.3.0.dist-info/WHEEL
zundler-0.3.0.dist-info/entry_points.txt
zundler-0.3.0.dist-info/licenses/LICENSE
zundler-0.3.0.dist-info/RECORD
