Metadata-Version: 2.4
Name: zundler
Version: 0.3.0
Summary: Bundle assets of distributed HTML docs into one self-contained HTML file
Project-URL: Homepage, https://github.com/AdrianVollmer/Zundler
Author-email: Adrian Vollmer <computerfluesterer@protonmail.com>
License-File: LICENSE
Classifier: Development Status :: 3 - Alpha
Classifier: Environment :: Console
Classifier: Environment :: Web Environment
Classifier: Intended Audience :: Developers
Classifier: License :: OSI Approved :: MIT License
Classifier: Operating System :: OS Independent
Classifier: Programming Language :: Python
Classifier: Programming Language :: Python :: 3
Classifier: Programming Language :: Python :: 3.8
Classifier: Programming Language :: Python :: 3.9
Classifier: Programming Language :: Python :: 3.10
Classifier: Programming Language :: Python :: 3.11
Classifier: Topic :: Documentation
Classifier: Topic :: Utilities
Requires-Python: >=3.8
Requires-Dist: python-magic
Provides-Extra: sphinx
Requires-Dist: sphinx; extra == 'sphinx'
